{
  "TV": [
    {
      "Title": "ERT1",
      "Image": "https://i.postimg.cc/C5csx9bG/ert1.png",
      "Video": "https://nbcnews2.akamaized.net/hls/live/723426/NBCNewsPlaymaker24x7Linear99a3a827-ua/master.m3u8",
      "isUnlocked": true
    },
    {
      "Title": "ERT2",
      "Image": "https://i.postimg.cc/ryjJjR7D/ert2.png",
      "Video": "https://nbcnews2.akamaized.net/hls/live/723426/NBCNewsPlaymaker24x7Linear99a3a827-ua/master.m3u8",
      "isUnlocked": true
    },
    {
      "Title": "ERT3",
      "Image": "https://i.postimg.cc/15YKhhmP/ert3.png",
      "Video": "https://nbcnews2.akamaized.net/hls/live/723426/NBCNewsPlaymaker24x7Linear99a3a827-ua/master.m3u8",
      "isUnlocked": true
    },
    {
      "Title": "MEGA",
      "Image": "https://i.postimg.cc/HLb0yrQs/mega.png",
      "Video": "https://nbcnews2.akamaized.net/hls/live/723426/NBCNewsPlaymaker24x7Linear99a3a827-ua/master.m3u8",
      "isUnlocked": true
    },
    {
      "Title": "STAR",
      "Image": "https://i.postimg.cc/sxH5r7RK/star.png",
      "Video": "https://nbcnews2.akamaized.net/hls/live/723426/NBCNewsPlaymaker24x7Linear99a3a827-ua/master.m3u8",
      "isUnlocked": true
    },
    {
      "Title": "ALPHA",
      "Image": "https://i.postimg.cc/L8Y3mC5P/alpha.png",
      "Video": "https://nbcnews2.akamaized.net/hls/live/723426/NBCNewsPlaymaker24x7Linear99a3a827-ua/master.m3u8",
      "isUnlocked": true
    },
    {
      "Title": "SKAI",
      "Image": "https://i.postimg.cc/Bbn2kNRX/skai.png",
      "Video": "https://nbcnews2.akamaized.net/hls/live/723426/NBCNewsPlaymaker24x7Linear99a3a827-ua/master.m3u8",
      "isUnlocked": true
    },
    {
      "Title": "OPEN",
      "Image": "https://i.postimg.cc/nzZ4YnkK/open.png",
      "Video": "https://nbcnews2.akamaized.net/hls/live/723426/NBCNewsPlaymaker24x7Linear99a3a827-ua/master.m3u8",
      "isUnlocked": true
    },
    {
      "Title": "VOULI",
      "Image": "https://i.postimg.cc/BQtxCYxz/vouli.png",
      "Video": "https://nbcnews2.akamaized.net/hls/live/723426/NBCNewsPlaymaker24x7Linear99a3a827-ua/master.m3u8",
      "isUnlocked": true
    },
    {
      "Title": "ONE CHANNEL",
      "Image": "https://i.postimg.cc/CMcGkTfD/one.png",
    "Video": "https://streaming.onetv.gr/show/onetv_high/index.m3u8",
      "isUnlocked": true
    },
    {
      "Title": "Kontra",
      "Image": "https://i.postimg.cc/YC5f06Ls/kontra.png",
      "Video": "https://streaming.onetv.gr/show/onetv_high/index.m3u8",
      "isUnlocked": true
    }
  ]
}
